{
	"class" : {
		 },
	"instance" : {
		"addBall" : "PL 1/31/2014 15:52:08.371",
		"collisionHandler" : "mb 1/30/2014 14:54",
		"collisionHandler:" : "mb 1/13/2014 21:42",
		"items" : "PS 1/27/2014 20:14:22.708",
		"items:" : "PS 1/27/2014 20:14:22.734",
		"lifes" : "PS 1/27/2014 20:14:22.587",
		"lifes:" : "PS 1/27/2014 20:14:22.634",
		"moveCapturedBallsBy:" : "mb 1/30/2014 23:22",
		"paddle" : "PS 1/27/2014 20:14:22.658",
		"paddle:" : "PS 1/27/2014 20:14:22.683",
		"releaseBalls" : "mb 1/30/2014 23:23",
		"remove:" : "tfel 5/9/2014 15:32",
		"resetBalls" : "PS 1/9/2014 14:41:10.7" } }
